UnicodeEngine_RPG/__init__.py
UnicodeEngine_RPG/chars.py
UnicodeEngine_RPG/getch.py
UnicodeEngine_RPG/inventory.py
UnicodeEngine_RPG/player.py
UnicodeEngine_RPG/utilities.py
UnicodeEngine_RPG-0.1.4.dist-info/LICENSE
UnicodeEngine_RPG-0.1.4.dist-info/METADATA
UnicodeEngine_RPG-0.1.4.dist-info/WHEEL
UnicodeEngine_RPG-0.1.4.dist-info/top_level.txt
UnicodeEngine_RPG-0.1.4.dist-info/RECORD
