Metadata-Version: 2.1
Name: UnicodeEngine-RPG
Version: 0.1.4
Summary: An engine that allows to render worlds and maps for console games based solely on Unicode.
Home-page: https://github.com/megat69/UnicodeEngine_RPG
Author: megat69
Project-URL: Bug Tracker, https://github.com/megat69/UnicodeEngine_RPG/issues
Classifier: Programming Language :: Python :: 3
Classifier: License :: OSI Approved :: MIT License
Classifier: Operating System :: OS Independent
Requires-Python: >=3.6
License-File: LICENSE
